column_diff/__init__.py
column_diff/column_diff.py
column_diff-0.1.1.dist-info/WHEEL
column_diff-0.1.1.dist-info/METADATA
column_diff-0.1.1.dist-info/RECORD
